lrslll/__init__.py
linhhh-1.0.0.dist-info/METADATA
linhhh-1.0.0.dist-info/WHEEL
linhhh-1.0.0.dist-info/top_level.txt
linhhh-1.0.0.dist-info/RECORD
