Metadata-Version: 2.1
Name: linhhh
Version: 1.0.0
Summary: This is lib
Home-page: http://lrsgzs.top
Author: lrs
Author-email: liurongshuo2022@outlook.com
License: MIT
Platform: UNKNOWN
